{
"autoplayBgm":false,"autoplayBgs":false,"battleback1Name":"Ship","battleback2Name":"Stone2","bgm":{"name":"","pan":0,"pitch":100,"volume":90},"bgs":{"name":"","pan":0,"pitch":100,"volume":90},"disableDashing":false,"displayName":"","encounterList":[],"encounterStep":30,"height":15,"note":"","parallaxLoopX":false,"parallaxLoopY":false,"parallaxName":"图书馆_0","parallaxShow":true,"parallaxSx":0,"parallaxSy":0,"scrollType":0,"specifyBattleback":false,"tilesetId":7,"width":14,
"data":[2816,2816,2816,2816,2816,2816,2816,2816,2816,2816,2816,2816,2816,2816,2816,2816,2816,2816,2816,2816,2816,2816,2816,2816,2816,2816,2816,2816,2816,2816,2816,2816,2816,2816,2816,2816,2816,2816,2816,2816,2816,2816,2816,2816,2816,2816,2816,2816,2816,2816,2816,2816,2816,2816,2816,2816,2816,2816,2816,2816,2816,2816,2816,2816,2816,2816,2816,2816,2816,2816,2816,2816,2816,2816,2816,2816,2816,2816,2816,2816,2816,2816,2816,2816,2816,2816,2816,2816,2816,2816,2816,2816,2816,2816,2816,2816,2816,2816,2816,2816,2816,2816,2816,2816,2816,2816,2816,2816,2816,2816,2816,2816,2816,2816,2816,2816,2816,2816,2816,2816,2816,2816,2816,2816,2816,2816,2816,2816,2816,2816,2816,2816,2816,2816,2816,2816,2816,2816,2816,2816,2816,2816,2816,2816,2816,2816,2816,2816,2816,2816,2816,2816,2816,2816,2816,2816,2816,2816,2816,2816,2816,2816,2816,2816,2816,2816,2816,2816,2816,2816,2816,2816,2816,2816,2816,2816,2816,2816,2816,2816,2816,2816,2816,2816,2816,2816,2816,2816,2816,2816,2816,2816,2816,2816,2816,2816,2816,2816,2816,2816,2816,2816,2816,2816,2816,2816,2816,2816,2816,2816,0,0,0,0,0,0,0,0,0,0,0,0,0,0,0,0,0,0,0,0,0,0,0,0,0,0,0,0,0,0,0,0,0,0,0,0,0,0,0,0,0,0,0,0,0,0,0,0,0,0,0,0,0,0,0,0,0,0,0,0,0,0,0,0,0,0,0,0,0,0,0,0,0,0,0,0,0,0,0,0,0,0,0,0,0,0,0,0,0,0,0,0,0,0,0,0,0,0,0,0,0,0,0,0,0,0,0,0,0,0,0,0,0,0,0,0,0,0,0,0,0,0,0,0,0,0,0,0,0,0,0,0,0,0,0,0,0,0,0,0,0,0,0,0,0,0,0,0,0,0,0,0,0,0,0,0,0,0,0,0,0,0,0,0,0,0,0,0,0,0,0,0,0,0,0,0,0,0,0,0,0,0,0,0,0,0,0,0,0,0,0,0,0,0,0,0,0,0,0,0,0,0,0,0,0,0,0,0,0,0,0,0,0,0,0,0,0,0,0,0,0,0,0,0,0,0,0,0,0,0,0,0,0,0,0,0,0,0,0,0,0,0,0,0,0,0,0,0,0,0,0,0,0,0,0,0,0,0,0,0,0,0,0,0,0,0,0,0,0,0,0,0,0,0,0,0,0,0,0,0,0,0,0,0,0,0,0,0,0,0,0,0,0,0,0,0,0,0,0,0,0,0,0,0,0,0,0,0,0,0,0,0,0,0,0,0,0,0,0,0,0,0,0,0,0,0,0,0,0,0,0,0,0,0,0,0,0,0,0,0,0,0,0,0,0,0,0,0,0,0,0,0,0,0,0,0,0,0,0,0,0,0,0,0,0,0,1,0,0,0,0,0,0,0,0,0,0,0,0,1,0,0,0,0,0,0,0,0,0,0,0,0,0,0,0,0,0,0,0,0,0,0,0,0,0,0,0,0,0,0,0,0,0,0,0,0,0,0,0,0,0,0,0,0,0,0,0,0,0,0,0,0,0,0,0,0,0,0,0,0,0,0,0,0,0,0,0,0,0,0,0,0,0,0,0,0,0,0,0,0,0,0,1,1,1,1,1,1,1,1,1,1,1,1,1,1,1,1,1,0,0,0,0,0,0,0,0,0,0,1,1,1,0,0,0,6,6,6,6,6,6,6,6,1,1,1,1,0,0,7,7,7,7,7,7,7,7,1,1,1,0,0,0,6,6,6,6,6,6,6,6,1,1,1,1,0,0,7,7,7,7,7,7,7,7,1,1,1,0,0,0,6,6,6,6,6,6,6,6,1,1,1,1,0,0,7,7,7,7,7,7,7,7,1,1,0,8,0,0,0,0,0,0,0,0,0,0,1,1,8,1,0,0,0,0,1,1,0,0,1,1,1,1,0,0,0,0,0,0,1,1,0,0,1,1,1,1,1,1,1,1,1,1,1,1,1,1,1,1,1,0,0,0,0,0,0,0,0,0,0,0,0,0,0,0,0,0,0,0,0,0,0,0,0,0,0,0,0,0,0,0,0,0,0,0,0,0,0,0,0,0,0,0,0,0,0,0,0,0,0,0,0,0,0,0,0,0,0,0,0,0,0,0,0,0,0,0,0,0,0,0,0,0,0,0,0,0,0,0,0,0,0,0,0,0,0,0,0,0,0,0,0,0,0,0,0,0,0,0,0,0,0,0,0,0,0,0,0,0,0,0,0,0,0,0,0,0,0,0,0,0,0,0,0,0,0,0,0,0,0,0,0,0,0,0,0,0,0,0,0,0,0,0,0,0,0,0,0,0,0,0,0,0,0,0,0,0,0,0,0,0,0,0,0,0,0,0,0,0,0,0,0,0,0,0,0,0,0,0,0,0,0,0,0,0,0,0,0,0,0,0,0,0,0,0,0,0,0,0,0,0,0,0,0,0,0,0,0,0,0,0,0,0,0,0,0,0,0,0,0,0,0,0,0,0,0,0,0,0,0,0,0,0,0,0,0,0,0,0,0,0,0,0,0,0,0,0,0,0,0,0,0,0,0,0,0,0,0,0,0,0,0,0,0,0,0,0,0,0,0,0,0,0,0,0,0,0,0,0,0,0,0,0,0,0,0,0,0,0,0,0,0,0,0,0,0,0,0,0,0,0,0,0,0,0,0,0,0,0,0,0,0,0,0,0,0,0,0,0,0,0,0,0,0,0,0,0,0,0,0,0,0,0,0,0,0,0,0,0,0,0,0,0,0,0,0,0,0,0,0,0,0,0,0,0,0,0,0,0,0,0,0,0,0,0,0,0,0,0,0,0,0,0,0,0,0,0,0,0,0,0,0,0,0,0,0,0,0,0,0,0,0,0,0,0,0,0,0,0,0,0,0,0,0,0,0,0,0,0,0,0,0,0,0,0,0,0,0,0,0],
"events":[
null,
{"id":1,"name":"科幻小说同学","note":"","pages":[{"conditions":{"actorId":1,"actorValid":false,"itemId":1,"itemValid":false,"selfSwitchCh":"A","selfSwitchValid":false,"switch1Id":1,"switch1Valid":false,"switch2Id":1,"switch2Valid":false,"variableId":1,"variableValid":false,"variableValue":0},"directionFix":false,"image":{"tileId":0,"characterName":"male_8","direction":8,"pattern":1,"characterIndex":0},"list":[{"code":108,"indent":0,"parameters":["<icon: talk>"]},{"code":101,"indent":0,"parameters":["",0,0,2]},{"code":401,"indent":0,"parameters":["|科幻小说同学 SF San"]},{"code":401,"indent":0,"parameters":["Have you read any SF books about looping or reincarnation before?"]},{"code":401,"indent":0,"parameters":["你有看过关于世间轮回的科幻小说吗？"]},{"code":101,"indent":0,"parameters":["",0,0,2]},{"code":401,"indent":0,"parameters":["|科幻小说同学 SF San"]},{"code":401,"indent":0,"parameters":["I found a book here a couple of days ago, the protagonist of the book is unconsciously involved in an infinitely looping test"]},{"code":401,"indent":0,"parameters":["前几天我在这里看到了一本，说主人公莫名其妙地被卷入了一场世间轮回的试炼"]},{"code":101,"indent":0,"parameters":["",0,0,2]},{"code":401,"indent":0,"parameters":["|科幻小说同学 SF San"]},{"code":401,"indent":0,"parameters":["And he loses all his memory when the looping starts"]},{"code":401,"indent":0,"parameters":["而且他发现自己竟失去了所有的记忆"]},{"code":101,"indent":0,"parameters":["",0,0,2]},{"code":401,"indent":0,"parameters":["|科幻小说同学 SF San"]},{"code":401,"indent":0,"parameters":["I haven't finished the book yet, but I cannot find it anywhere now"]},{"code":401,"indent":0,"parameters":["后来的故事我还没看到，但我现在不知道为啥找不到那本书了"]},{"code":123,"indent":0,"parameters":["A",0]},{"code":0,"indent":0,"parameters":[]}],"moveFrequency":3,"moveRoute":{"list":[{"code":0,"parameters":[]}],"repeat":true,"skippable":false,"wait":false},"moveSpeed":3,"moveType":0,"priorityType":1,"stepAnime":false,"through":false,"trigger":0,"walkAnime":true},{"conditions":{"actorId":1,"actorValid":false,"itemId":1,"itemValid":false,"selfSwitchCh":"A","selfSwitchValid":true,"switch1Id":1,"switch1Valid":false,"switch2Id":1,"switch2Valid":false,"variableId":1,"variableValid":false,"variableValue":0},"directionFix":true,"image":{"tileId":0,"characterName":"male_8","direction":8,"pattern":1,"characterIndex":0},"list":[{"code":108,"indent":0,"parameters":["<icon: talk>"]},{"code":101,"indent":0,"parameters":["",0,0,2]},{"code":401,"indent":0,"parameters":["|科幻小说同学 SF San"]},{"code":401,"indent":0,"parameters":["Why?"]},{"code":401,"indent":0,"parameters":["为什么呢"]},{"code":0,"indent":0,"parameters":[]}],"moveFrequency":3,"moveRoute":{"list":[{"code":0,"parameters":[]}],"repeat":true,"skippable":false,"wait":false},"moveSpeed":3,"moveType":0,"priorityType":1,"stepAnime":false,"through":false,"trigger":0,"walkAnime":true}],"x":6,"y":6},
{"id":2,"name":"安静的同学","note":"","pages":[{"conditions":{"actorId":1,"actorValid":false,"itemId":1,"itemValid":false,"selfSwitchCh":"A","selfSwitchValid":false,"switch1Id":1,"switch1Valid":false,"switch2Id":1,"switch2Valid":false,"variableId":1,"variableValid":false,"variableValue":0},"directionFix":true,"image":{"tileId":0,"characterName":"library_sit","direction":2,"pattern":1,"characterIndex":0},"list":[{"code":108,"indent":0,"parameters":["<icon: talk>"]},{"code":101,"indent":0,"parameters":["",0,0,2]},{"code":401,"indent":0,"parameters":["|安静的同学 Quite San"]},{"code":401,"indent":0,"parameters":["This Reading Room is the best place to take a nap at noon"]},{"code":401,"indent":0,"parameters":["安静的图书馆最适合中午睡觉了"]},{"code":0,"indent":0,"parameters":[]}],"moveFrequency":3,"moveRoute":{"list":[{"code":0,"parameters":[]}],"repeat":true,"skippable":false,"wait":false},"moveSpeed":3,"moveType":0,"priorityType":1,"stepAnime":false,"through":false,"trigger":0,"walkAnime":true}],"x":12,"y":11},
{"id":3,"name":"1F","note":"","pages":[{"conditions":{"actorId":1,"actorValid":false,"itemId":1,"itemValid":false,"selfSwitchCh":"A","selfSwitchValid":false,"switch1Id":1,"switch1Valid":false,"switch2Id":1,"switch2Valid":false,"variableId":1,"variableValid":false,"variableValue":0},"directionFix":false,"image":{"characterIndex":0,"characterName":"","direction":2,"pattern":0,"tileId":0},"list":[{"code":108,"indent":0,"parameters":["<icon: move>"]},{"code":408,"indent":0,"parameters":["<cn: 教学楼-1F>"]},{"code":408,"indent":0,"parameters":["<en: Teaching Building - 1F>"]},{"code":250,"indent":0,"parameters":[{"name":"classroom door","volume":90,"pitch":100,"pan":0}]},{"code":201,"indent":0,"parameters":[0,136,2,25,6,0]},{"code":0,"indent":0,"parameters":[]}],"moveFrequency":3,"moveRoute":{"list":[{"code":0,"parameters":[]}],"repeat":true,"skippable":false,"wait":false},"moveSpeed":3,"moveType":0,"priorityType":1,"stepAnime":false,"through":false,"trigger":0,"walkAnime":true}],"x":3,"y":14},
{"id":4,"name":"1F","note":"","pages":[{"conditions":{"actorId":1,"actorValid":false,"itemId":1,"itemValid":false,"selfSwitchCh":"A","selfSwitchValid":false,"switch1Id":1,"switch1Valid":false,"switch2Id":1,"switch2Valid":false,"variableId":1,"variableValid":false,"variableValue":0},"directionFix":false,"image":{"characterIndex":0,"characterName":"","direction":2,"pattern":0,"tileId":0},"list":[{"code":108,"indent":0,"parameters":["<icon: move>"]},{"code":408,"indent":0,"parameters":["<cn: 教学楼-1F>"]},{"code":408,"indent":0,"parameters":["<en: Teaching Building - 1F>"]},{"code":250,"indent":0,"parameters":[{"name":"classroom door","volume":90,"pitch":100,"pan":0}]},{"code":201,"indent":0,"parameters":[0,136,2,24,6,0]},{"code":0,"indent":0,"parameters":[]}],"moveFrequency":3,"moveRoute":{"list":[{"code":0,"parameters":[]}],"repeat":true,"skippable":false,"wait":false},"moveSpeed":3,"moveType":0,"priorityType":1,"stepAnime":false,"through":false,"trigger":0,"walkAnime":true}],"x":4,"y":14},
{"id":5,"name":"图书馆管理员","note":"","pages":[{"conditions":{"actorId":1,"actorValid":false,"itemId":1,"itemValid":false,"selfSwitchCh":"A","selfSwitchValid":false,"switch1Id":1,"switch1Valid":false,"switch2Id":1,"switch2Valid":false,"variableId":1,"variableValid":false,"variableValue":0},"directionFix":false,"image":{"tileId":0,"characterName":"female_3","direction":6,"pattern":1,"characterIndex":0},"list":[{"code":0,"indent":0,"parameters":[]}],"moveFrequency":3,"moveRoute":{"list":[{"code":0,"parameters":[]}],"repeat":true,"skippable":false,"wait":false},"moveSpeed":3,"moveType":0,"priorityType":1,"stepAnime":false,"through":false,"trigger":0,"walkAnime":true}],"x":1,"y":11},
{"id":6,"name":"剧情","note":"","pages":[{"conditions":{"actorId":1,"actorValid":false,"itemId":1,"itemValid":false,"selfSwitchCh":"A","selfSwitchValid":false,"switch1Id":1,"switch1Valid":false,"switch2Id":1,"switch2Valid":false,"variableId":1,"variableValid":false,"variableValue":0},"directionFix":false,"image":{"characterIndex":0,"characterName":"","direction":2,"pattern":0,"tileId":0},"list":[{"code":213,"indent":0,"parameters":[-1,8,true]},{"code":205,"indent":0,"parameters":[-1,{"list":[{"code":18,"indent":null},{"code":15,"parameters":[30],"indent":null},{"code":4,"indent":null},{"code":4,"indent":null},{"code":4,"indent":null},{"code":4,"indent":null},{"code":4,"indent":null},{"code":4,"indent":null},{"code":4,"indent":null},{"code":18,"indent":null},{"code":15,"parameters":[30],"indent":null},{"code":0}],"repeat":false,"skippable":false,"wait":true}]},{"code":505,"indent":0,"parameters":[{"code":18,"indent":null}]},{"code":505,"indent":0,"parameters":[{"code":15,"parameters":[30],"indent":null}]},{"code":505,"indent":0,"parameters":[{"code":4,"indent":null}]},{"code":505,"indent":0,"parameters":[{"code":4,"indent":null}]},{"code":505,"indent":0,"parameters":[{"code":4,"indent":null}]},{"code":505,"indent":0,"parameters":[{"code":4,"indent":null}]},{"code":505,"indent":0,"parameters":[{"code":4,"indent":null}]},{"code":505,"indent":0,"parameters":[{"code":4,"indent":null}]},{"code":505,"indent":0,"parameters":[{"code":4,"indent":null}]},{"code":505,"indent":0,"parameters":[{"code":18,"indent":null}]},{"code":505,"indent":0,"parameters":[{"code":15,"parameters":[30],"indent":null}]},{"code":213,"indent":0,"parameters":[-1,8,true]},{"code":101,"indent":0,"parameters":["",0,0,2,""]},{"code":401,"indent":0,"parameters":["|0|汐/正常-疑惑"]},{"code":401,"indent":0,"parameters":["Huh? It doesn't seem to be here"]},{"code":401,"indent":0,"parameters":["嗯？好像不在这里"]},{"code":401,"indent":0,"parameters":[""]},{"code":101,"indent":0,"parameters":["",0,0,2,""]},{"code":401,"indent":0,"parameters":["|0|汐/正常-疑惑"]},{"code":401,"indent":0,"parameters":["Go back to the square and have a look"]},{"code":401,"indent":0,"parameters":["回去广场看看吧"]},{"code":401,"indent":0,"parameters":[""]},{"code":101,"indent":0,"parameters":["",0,0,2,""]},{"code":401,"indent":0,"parameters":["|0|汐/正常-无表情"]},{"code":401,"indent":0,"parameters":["Oh, by the way, take some books"]},{"code":401,"indent":0,"parameters":["哦对了，顺便搬几本书"]},{"code":205,"indent":0,"parameters":[-1,{"list":[{"code":1,"indent":null},{"code":1,"indent":null},{"code":1,"indent":null},{"code":1,"indent":null},{"code":1,"indent":null},{"code":17,"indent":null},{"code":0}],"repeat":false,"skippable":false,"wait":true}]},{"code":505,"indent":0,"parameters":[{"code":1,"indent":null}]},{"code":505,"indent":0,"parameters":[{"code":1,"indent":null}]},{"code":505,"indent":0,"parameters":[{"code":1,"indent":null}]},{"code":505,"indent":0,"parameters":[{"code":1,"indent":null}]},{"code":505,"indent":0,"parameters":[{"code":1,"indent":null}]},{"code":505,"indent":0,"parameters":[{"code":17,"indent":null}]},{"code":101,"indent":0,"parameters":["",0,0,2,""]},{"code":401,"indent":0,"parameters":["|0|汐/正常-无表情"]},{"code":401,"indent":0,"parameters":["Hello, I'm from SOS Supernatural Research Club"]},{"code":401,"indent":0,"parameters":["你好，我是超自然研究部的"]},{"code":401,"indent":0,"parameters":[""]},{"code":101,"indent":0,"parameters":["",0,0,2,""]},{"code":401,"indent":0,"parameters":["|图书馆管理员 Librarian"]},{"code":401,"indent":0,"parameters":["Huh? Not enough?"]},{"code":401,"indent":0,"parameters":["嗯？还不够吗？"]},{"code":101,"indent":0,"parameters":["",0,0,2,""]},{"code":401,"indent":0,"parameters":["|图书馆管理员 Librarian"]},{"code":401,"indent":0,"parameters":["That classmate has borrowed so many books by trolley just now"]},{"code":401,"indent":0,"parameters":["刚才那位同学都已经用小推车借走那么多了"]},{"code":101,"indent":0,"parameters":["",0,0,2,""]},{"code":401,"indent":0,"parameters":["|图书馆管理员 Librarian"]},{"code":401,"indent":0,"parameters":["I can only give you these"]},{"code":401,"indent":0,"parameters":["就只能再给你这几本了"]},{"code":101,"indent":0,"parameters":["",0,0,2,""]},{"code":401,"indent":0,"parameters":["|图书馆管理员 Librarian"]},{"code":401,"indent":0,"parameters":["All those strange books in the library have been given to you"]},{"code":401,"indent":0,"parameters":["图书馆里那些奇怪的书已经全都给你们了"]},{"code":101,"indent":0,"parameters":["",0,0,2,""]},{"code":401,"indent":0,"parameters":["|0|汐/正常-发觉张口"]},{"code":401,"indent":0,"parameters":["Ah... well, thank you"]},{"code":401,"indent":0,"parameters":["啊…嗯好的，谢谢"]},{"code":401,"indent":0,"parameters":[""]},{"code":101,"indent":0,"parameters":["",0,0,2,""]},{"code":401,"indent":0,"parameters":["|图书馆管理员 Librarian"]},{"code":401,"indent":0,"parameters":["Remember not to return it at that time, just put it in your activity room"]},{"code":401,"indent":0,"parameters":["记得到时候不要还回来，直接放到你们活动室去吧"]},{"code":101,"indent":0,"parameters":["",0,0,2,""]},{"code":401,"indent":0,"parameters":["|0|汐/震惊-思考"]},{"code":401,"indent":0,"parameters":["What?"]},{"code":401,"indent":0,"parameters":["哈？"]},{"code":401,"indent":0,"parameters":[""]},{"code":101,"indent":0,"parameters":["",0,0,2,""]},{"code":401,"indent":0,"parameters":["|0|汐/正常-发觉"]},{"code":401,"indent":0,"parameters":["(How the books are so strange that they are abanded)"]},{"code":401,"indent":0,"parameters":["(到底是什么书那么让人嫌弃)"]},{"code":231,"indent":0,"parameters":[1,"2_母猫的产后护理",0,0,0,0,100,100,0,0]},{"code":232,"indent":0,"parameters":[1,0,0,0,0,0,100,100,255,0,30,true,0]},{"code":101,"indent":0,"parameters":["",0,0,2,""]},{"code":401,"indent":0,"parameters":["11"]},{"code":401,"indent":0,"parameters":["Postnatal care of female cats"]},{"code":401,"indent":0,"parameters":["母猫的产后护理"]},{"code":232,"indent":0,"parameters":[1,0,0,0,0,0,100,100,0,0,10,true,0]},{"code":231,"indent":0,"parameters":[1,"2_LSP是怎么炼成的",0,0,0,0,100,100,0,0]},{"code":232,"indent":0,"parameters":[1,0,0,0,0,0,100,100,255,0,30,true,0]},{"code":101,"indent":0,"parameters":["",0,0,2,""]},{"code":401,"indent":0,"parameters":["11"]},{"code":401,"indent":0,"parameters":["How the make a LSP"]},{"code":401,"indent":0,"parameters":["LSP是怎么练成的"]},{"code":232,"indent":0,"parameters":[1,0,0,0,0,0,100,100,0,0,10,true,0]},{"code":231,"indent":0,"parameters":[1,"2_发酸王牛奶不会梦到Debu粉猫",0,0,0,0,100,100,0,0]},{"code":232,"indent":0,"parameters":[1,0,0,0,0,0,100,100,255,0,30,true,0]},{"code":101,"indent":0,"parameters":["",0,0,2,""]},{"code":401,"indent":0,"parameters":["11"]},{"code":401,"indent":0,"parameters":["Sour King Milk won't dream of Debu Pink Cat"]},{"code":401,"indent":0,"parameters":["发酸王牛奶不会梦到Debu粉猫"]},{"code":232,"indent":0,"parameters":[1,0,0,0,0,0,100,100,0,0,10,true,0]},{"code":231,"indent":0,"parameters":[1,"2_牛奶与猫之歌",0,0,0,0,100,100,0,0]},{"code":232,"indent":0,"parameters":[1,0,0,0,0,0,100,100,255,0,30,true,0]},{"code":101,"indent":0,"parameters":["",0,0,2,""]},{"code":401,"indent":0,"parameters":["11"]},{"code":401,"indent":0,"parameters":["Song of milk and cat"]},{"code":401,"indent":0,"parameters":["牛奶与猫之歌"]},{"code":232,"indent":0,"parameters":[1,0,0,0,0,0,100,100,0,0,10,true,0]},{"code":231,"indent":0,"parameters":[1,"2_撒硕指南",0,0,0,0,100,100,0,0]},{"code":232,"indent":0,"parameters":[1,0,0,0,0,0,100,100,255,0,30,true,0]},{"code":101,"indent":0,"parameters":["",0,0,2,""]},{"code":401,"indent":0,"parameters":["11"]},{"code":401,"indent":0,"parameters":["Toilet group guide"]},{"code":401,"indent":0,"parameters":["撒硕指南"]},{"code":232,"indent":0,"parameters":[1,0,0,0,0,0,100,100,0,0,10,true,0]},{"code":101,"indent":0,"parameters":["",0,0,2,""]},{"code":401,"indent":0,"parameters":["|0|汐/震惊-思考"]},{"code":401,"indent":0,"parameters":["Holy..."]},{"code":401,"indent":0,"parameters":["啊这…"]},{"code":235,"indent":0,"parameters":[1]},{"code":126,"indent":0,"parameters":[24,0,0,1]},{"code":126,"indent":0,"parameters":[25,0,0,1]},{"code":126,"indent":0,"parameters":[26,0,0,1]},{"code":126,"indent":0,"parameters":[27,0,0,1]},{"code":126,"indent":0,"parameters":[28,0,0,1]},{"code":201,"indent":0,"parameters":[0,132,37,8,2,0]},{"code":357,"indent":0,"parameters":["Tool","设置提示","设置提示",{"en":"Take the book back to the tent","cn":"把书拿回帐篷吧","time":"3000"}]},{"code":657,"indent":0,"parameters":["en = Take the book back to the tent"]},{"code":657,"indent":0,"parameters":["cn = 把书拿回帐篷吧"]},{"code":657,"indent":0,"parameters":["time = 3000"]},{"code":0,"indent":0,"parameters":[]}],"moveFrequency":3,"moveRoute":{"list":[{"code":0,"parameters":[]}],"repeat":true,"skippable":false,"wait":false},"moveSpeed":3,"moveType":0,"priorityType":0,"stepAnime":false,"through":false,"trigger":3,"walkAnime":true}],"x":0,"y":14}
]
}