{
"autoplayBgm":true,"autoplayBgs":false,"battleback1Name":"","battleback2Name":"","bgm":{"name":"Jazz&funny","pan":0,"pitch":100,"volume":20},"bgs":{"name":"","pan":0,"pitch":100,"volume":90},"disableDashing":false,"displayName":"","encounterList":[],"encounterStep":30,"height":13,"note":"<ulds> {\n\"name\": \"restroom_nan_0\",\n\"x\": \"this.rx(0)\",\n\"y\": \"this.ry(0)\"\n} </ulds>\n<ulds> {\n\"name\": \"restroom_nan_1\",\n\"x\": \"this.rx(0)\",\n\"y\": \"this.ry(0)\",\n\"z\": \"9\"\n} </ulds>\n","parallaxLoopX":false,"parallaxLoopY":false,"parallaxName":"restroom_nan","parallaxShow":true,"parallaxSx":0,"parallaxSy":0,"scrollType":0,"specifyBattleback":false,"tilesetId":7,"width":10,
"data":[3200,3200,3200,3200,3200,3200,3200,3200,3200,3200,3200,3200,3200,3200,3200,3200,3200,3200,3200,3200,3200,3200,3200,3200,3200,3200,3200,3200,3200,3200,3200,3200,3200,3200,3200,3200,3200,3200,3200,3200,3200,3200,3200,3200,3200,3200,3200,3200,3200,3200,3200,3200,3200,3200,3200,3200,3200,3200,3200,3200,3200,3200,3200,3200,3200,3200,3200,3200,3200,3200,3200,3200,3200,3200,3200,3200,3200,3200,3200,3200,3200,3200,3200,3200,3200,3200,3200,3200,3200,3200,3200,3200,3200,3200,3200,3200,3200,3200,3200,3200,3200,3200,3200,3200,3200,3200,3200,3200,3200,3200,3200,3200,3200,3200,3200,3200,3200,3200,3200,3200,3200,3200,3200,3200,3200,3200,3200,3200,3200,3200,0,0,0,0,0,0,0,0,0,0,0,0,0,0,0,0,0,0,0,0,0,0,0,0,0,0,0,0,0,0,0,0,0,0,0,0,0,0,0,0,0,0,0,0,0,0,0,0,0,0,0,0,0,0,0,0,0,0,0,0,0,0,0,0,0,0,0,0,0,0,0,0,0,0,0,0,0,0,0,0,0,0,0,0,0,0,0,0,0,0,0,0,0,0,0,0,0,0,0,0,0,0,0,0,0,0,0,0,0,0,0,0,0,0,0,0,0,0,0,0,0,0,0,0,0,0,0,0,0,0,0,0,0,0,0,0,0,0,0,0,0,0,0,0,0,0,0,0,0,0,0,0,0,0,0,0,0,0,0,0,0,0,0,0,0,0,0,0,0,0,0,0,0,0,0,0,0,0,0,0,0,0,0,0,0,0,0,0,0,0,0,0,0,0,0,0,0,0,0,0,0,0,0,0,0,0,0,0,0,0,0,0,0,0,0,0,0,0,0,0,0,0,0,0,0,0,0,0,0,0,0,0,0,0,0,0,0,0,0,0,0,0,0,0,0,0,0,0,0,0,0,0,0,0,0,0,0,0,0,0,0,0,0,0,0,0,0,0,0,0,0,1,1,1,1,1,1,1,1,0,0,1,1,1,1,1,1,1,1,0,0,1,0,0,0,0,0,1,1,0,0,1,0,0,0,0,0,1,1,0,0,1,0,0,0,0,0,1,1,0,0,1,0,0,0,0,0,1,1,0,0,1,0,0,0,0,0,1,1,0,0,1,1,0,0,0,0,1,1,0,0,1,0,0,0,0,0,1,1,1,0,1,0,0,0,0,0,0,0,1,0,1,0,0,0,0,0,0,0,1,0,1,1,1,0,0,1,1,1,1,0,0,0,0,0,0,0,0,0,0,0,0,0,0,0,0,0,0,0,0,0,0,0,0,0,0,0,0,0,0,0,0,0,0,0,0,0,0,0,0,0,0,0,0,0,0,0,0,0,0,0,0,0,0,0,0,0,0,0,0,0,0,0,0,0,0,0,0,0,0,0,0,0,0,0,0,0,0,0,0,0,0,0,0,0,0,0,0,0,0,0,0,0,0,0,0,0,0,0,0,0,0,0,0,0,0,0,0,0,0,0,0,0,0,0,0,0,0,0,0,0,0,0,0,0,0,0,0,0,0,0,0,0,0,0,0,0,0,0,0,0,0,0,0,0,0,0,0,0,0,0,0,0,0,0,0,0,0,0,0,0,0,0,0,0,0,0,0,0,0,0,0,0,0,0,0,0,0,0,0,0,0,0,0,0,0,0,0,0,0,0,0,0,0,0,0,0,0,0,0,0,0,0,0,0,0,0,0,0,0,0,0,0,0,0,0,0,0,0,0,0,0,0,0,0,0,0,0,0,0,0,0,0,0,0,0,0,0,0,0,0,0,0,0,0,0,0,0,0,0,0,0,0,0,0,0,0,0,0,0],
"events":[
null,
{"id":1,"name":"EV001","note":"","pages":[{"conditions":{"actorId":1,"actorValid":false,"itemId":1,"itemValid":false,"selfSwitchCh":"A","selfSwitchValid":false,"switch1Id":1,"switch1Valid":false,"switch2Id":1,"switch2Valid":false,"variableId":1,"variableValid":false,"variableValue":0},"directionFix":false,"image":{"characterIndex":0,"characterName":"","direction":2,"pattern":0,"tileId":0},"list":[{"code":211,"indent":0,"parameters":[0]},{"code":201,"indent":0,"parameters":[0,21,29,13,2,0]},{"code":0,"indent":0,"parameters":[]}],"moveFrequency":3,"moveRoute":{"list":[{"code":0,"parameters":[]}],"repeat":true,"skippable":false,"wait":false},"moveSpeed":3,"moveType":0,"priorityType":0,"stepAnime":false,"through":false,"trigger":1,"walkAnime":true},{"conditions":{"actorId":1,"actorValid":false,"itemId":1,"itemValid":false,"selfSwitchCh":"A","selfSwitchValid":false,"switch1Id":13,"switch1Valid":true,"switch2Id":1,"switch2Valid":false,"variableId":1,"variableValid":false,"variableValue":0},"directionFix":false,"image":{"characterIndex":0,"characterName":"","direction":2,"pattern":0,"tileId":0},"list":[{"code":101,"indent":0,"parameters":["Hiiro",0,0,2]},{"code":401,"indent":0,"parameters":["\\n<汐 Shio>"]},{"code":401,"indent":0,"parameters":["\\}I can’t hold on anymore...\\{<br>"]},{"code":401,"indent":0,"parameters":["快憋不住了……"]},{"code":205,"indent":0,"parameters":[-1,{"list":[{"code":13,"indent":null},{"code":0}],"repeat":false,"skippable":false,"wait":true}]},{"code":505,"indent":0,"parameters":[{"code":13,"indent":null}]},{"code":0,"indent":0,"parameters":[]}],"moveFrequency":3,"moveRoute":{"list":[{"code":0,"parameters":[]}],"repeat":true,"skippable":false,"wait":false},"moveSpeed":3,"moveType":0,"priorityType":0,"stepAnime":false,"through":false,"trigger":1,"walkAnime":true}],"x":4,"y":12},
{"id":2,"name":"EV002","note":"","pages":[{"conditions":{"actorId":1,"actorValid":false,"itemId":1,"itemValid":false,"selfSwitchCh":"A","selfSwitchValid":false,"switch1Id":1,"switch1Valid":false,"switch2Id":1,"switch2Valid":false,"variableId":1,"variableValid":false,"variableValue":0},"directionFix":false,"image":{"characterIndex":0,"characterName":"","direction":2,"pattern":0,"tileId":0},"list":[{"code":211,"indent":0,"parameters":[0]},{"code":201,"indent":0,"parameters":[0,21,29,13,2,0]},{"code":0,"indent":0,"parameters":[]}],"moveFrequency":3,"moveRoute":{"list":[{"code":0,"parameters":[]}],"repeat":true,"skippable":false,"wait":false},"moveSpeed":3,"moveType":0,"priorityType":0,"stepAnime":false,"through":false,"trigger":1,"walkAnime":true},{"conditions":{"actorId":1,"actorValid":false,"itemId":1,"itemValid":false,"selfSwitchCh":"A","selfSwitchValid":false,"switch1Id":13,"switch1Valid":true,"switch2Id":1,"switch2Valid":false,"variableId":1,"variableValid":false,"variableValue":0},"directionFix":false,"image":{"characterIndex":0,"characterName":"","direction":2,"pattern":0,"tileId":0},"list":[{"code":101,"indent":0,"parameters":["Hiiro",0,0,2]},{"code":401,"indent":0,"parameters":["\\n<汐 Shio>"]},{"code":401,"indent":0,"parameters":["\\}I can’t hold on anymore...\\{<br>"]},{"code":401,"indent":0,"parameters":["快憋不住了……"]},{"code":205,"indent":0,"parameters":[-1,{"list":[{"code":13,"indent":null},{"code":0}],"repeat":false,"skippable":false,"wait":true}]},{"code":505,"indent":0,"parameters":[{"code":13,"indent":null}]},{"code":0,"indent":0,"parameters":[]}],"moveFrequency":3,"moveRoute":{"list":[{"code":0,"parameters":[]}],"repeat":true,"skippable":false,"wait":false},"moveSpeed":3,"moveType":0,"priorityType":0,"stepAnime":false,"through":false,"trigger":1,"walkAnime":true}],"x":5,"y":12},
{"id":3,"name":"EV003","note":"","pages":[{"conditions":{"actorId":1,"actorValid":false,"itemId":1,"itemValid":false,"selfSwitchCh":"A","selfSwitchValid":false,"switch1Id":1,"switch1Valid":false,"switch2Id":1,"switch2Valid":false,"variableId":1,"variableValid":false,"variableValue":0},"directionFix":false,"image":{"characterIndex":0,"characterName":"","direction":2,"pattern":0,"tileId":0},"list":[{"code":108,"indent":0,"parameters":["<actionIcon: 188>"]},{"code":101,"indent":0,"parameters":["",0,1,1]},{"code":401,"indent":0,"parameters":["<br>"]},{"code":401,"indent":0,"parameters":["\\}\\#There’s a water bucket right next to the sink\\{<br>"]},{"code":401,"indent":0,"parameters":["洗手池旁边放着一个水桶"]},{"code":101,"indent":0,"parameters":["",0,1,1]},{"code":401,"indent":0,"parameters":["<br>"]},{"code":401,"indent":0,"parameters":["\\}\\#And there’s a bailer inside the bucket. What is it for?\\{<br>"]},{"code":401,"indent":0,"parameters":["水桶里有水瓢，但不知道有什么作用……"]},{"code":123,"indent":0,"parameters":["A",0]},{"code":0,"indent":0,"parameters":[]}],"moveFrequency":3,"moveRoute":{"list":[{"code":0,"parameters":[]}],"repeat":true,"skippable":false,"wait":false},"moveSpeed":3,"moveType":0,"priorityType":1,"stepAnime":false,"through":false,"trigger":0,"walkAnime":true},{"conditions":{"actorId":1,"actorValid":false,"itemId":1,"itemValid":false,"selfSwitchCh":"A","selfSwitchValid":true,"switch1Id":1,"switch1Valid":false,"switch2Id":1,"switch2Valid":false,"variableId":1,"variableValid":false,"variableValue":0},"directionFix":false,"image":{"characterIndex":0,"characterName":"","direction":2,"pattern":0,"tileId":0},"list":[{"code":0,"indent":0,"parameters":[]}],"moveFrequency":3,"moveRoute":{"list":[{"code":0,"parameters":[]}],"repeat":true,"skippable":false,"wait":false},"moveSpeed":3,"moveType":0,"priorityType":0,"stepAnime":false,"through":false,"trigger":0,"walkAnime":true}],"x":2,"y":8},
{"id":4,"name":"EV004","note":"","pages":[{"conditions":{"actorId":1,"actorValid":false,"itemId":1,"itemValid":false,"selfSwitchCh":"A","selfSwitchValid":false,"switch1Id":1,"switch1Valid":false,"switch2Id":1,"switch2Valid":false,"variableId":1,"variableValid":false,"variableValue":0},"directionFix":false,"image":{"characterIndex":0,"characterName":"","direction":2,"pattern":0,"tileId":0},"list":[{"code":101,"indent":0,"parameters":["Hiiro",0,0,2]},{"code":401,"indent":0,"parameters":["\\n<\\N[1]>"]},{"code":401,"indent":0,"parameters":["\\}The inner most room should be the safest... Those at the outside can be spotted easily...\\{<br>"]},{"code":401,"indent":0,"parameters":["最里面那个隔间应该比较安全……靠外面的话可能会被发现……"]},{"code":101,"indent":0,"parameters":["Hiiro",0,0,2]},{"code":401,"indent":0,"parameters":["\\n<\\N[1]>"]},{"code":401,"indent":0,"parameters":["\\}Well there’s no difference actually... But I still feel that the inner most one is the best...\\{<br>"]},{"code":401,"indent":0,"parameters":["其实没有什么区别……但还是感觉里面那个好……"]},{"code":101,"indent":0,"parameters":["Hiiro",0,0,2]},{"code":401,"indent":0,"parameters":["\\n<\\N[1]>"]},{"code":401,"indent":0,"parameters":["\\}I should go that one...\\{<br>"]},{"code":401,"indent":0,"parameters":["去最里面那个隔间吧……"]},{"code":123,"indent":0,"parameters":["A",0]},{"code":0,"indent":0,"parameters":[]}],"moveFrequency":3,"moveRoute":{"list":[{"code":0,"parameters":[]}],"repeat":true,"skippable":false,"wait":false},"moveSpeed":3,"moveType":0,"priorityType":0,"stepAnime":false,"through":false,"trigger":3,"walkAnime":true},{"conditions":{"actorId":1,"actorValid":false,"itemId":1,"itemValid":false,"selfSwitchCh":"A","selfSwitchValid":true,"switch1Id":1,"switch1Valid":false,"switch2Id":1,"switch2Valid":false,"variableId":1,"variableValid":false,"variableValue":0},"directionFix":false,"image":{"characterIndex":0,"characterName":"","direction":2,"pattern":0,"tileId":0},"list":[{"code":0,"indent":0,"parameters":[]}],"moveFrequency":3,"moveRoute":{"list":[{"code":0,"parameters":[]}],"repeat":true,"skippable":false,"wait":false},"moveSpeed":3,"moveType":0,"priorityType":0,"stepAnime":false,"through":false,"trigger":0,"walkAnime":true}],"x":0,"y":12},
{"id":5,"name":"EV005","note":"","pages":[{"conditions":{"actorId":1,"actorValid":false,"itemId":1,"itemValid":false,"selfSwitchCh":"A","selfSwitchValid":false,"switch1Id":1,"switch1Valid":false,"switch2Id":1,"switch2Valid":false,"variableId":1,"variableValid":false,"variableValue":0},"directionFix":false,"image":{"characterIndex":0,"characterName":"","direction":2,"pattern":0,"tileId":0},"list":[{"code":108,"indent":0,"parameters":["<actionIcon: 188>"]},{"code":221,"indent":0,"parameters":[]},{"code":101,"indent":0,"parameters":["Hiiro",0,0,2]},{"code":401,"indent":0,"parameters":["\\n<汐 Shio>"]},{"code":401,"indent":0,"parameters":["\\}WuWuWuWuWuWu\\{<br>"]},{"code":401,"indent":0,"parameters":["呜呜呜呜呜呜呜"]},{"code":101,"indent":0,"parameters":["Hiiro",0,0,2]},{"code":401,"indent":0,"parameters":["\\n<汐 Shio>"]},{"code":401,"indent":0,"parameters":["\\}How can this be...\\{<br>"]},{"code":401,"indent":0,"parameters":["怎么会这样……"]},{"code":101,"indent":0,"parameters":["Hiiro",0,0,2]},{"code":401,"indent":0,"parameters":["\\n<汐 Shio>"]},{"code":401,"indent":0,"parameters":["\\}All lady’s restrooms are in maintenance at this most critical moment\\{<br>"]},{"code":401,"indent":0,"parameters":["在关键时候全部的女生厕所都坏了"]},{"code":101,"indent":0,"parameters":["Hiiro",0,0,2]},{"code":401,"indent":0,"parameters":["\\n<汐 Shio>"]},{"code":401,"indent":0,"parameters":["\\}But isn’t it too strange?\\{<br>"]},{"code":401,"indent":0,"parameters":["而且说到底这也太奇怪了吧？"]},{"code":101,"indent":0,"parameters":["Hiiro",0,0,2]},{"code":401,"indent":0,"parameters":["\\n<汐 Shio>"]},{"code":401,"indent":0,"parameters":["\\}How can they do it at the same time? \\{<br>"]},{"code":401,"indent":0,"parameters":["怎么可能同一时间两个女厕都坏了"]},{"code":101,"indent":0,"parameters":["Hiiro",0,0,2]},{"code":401,"indent":0,"parameters":["\\n<汐 Shio>"]},{"code":401,"indent":0,"parameters":["\\}This is definitely weird!!\\{<br>"]},{"code":401,"indent":0,"parameters":["这也太不正常了点吧！！"]},{"code":101,"indent":0,"parameters":["Hiiro",0,0,2]},{"code":401,"indent":0,"parameters":["\\n<汐 Shio>"]},{"code":401,"indent":0,"parameters":["\\}Well but anyhow, problem solved\\{<br>"]},{"code":401,"indent":0,"parameters":["哎，无论如何，反正解决了"]},{"code":101,"indent":0,"parameters":["Hiiro",0,0,2]},{"code":401,"indent":0,"parameters":["\\n<汐 Shio>"]},{"code":401,"indent":0,"parameters":["\\}Toilet roll toilet roll...\\{<br>"]},{"code":401,"indent":0,"parameters":["纸巾纸巾……"]},{"code":101,"indent":0,"parameters":["Hiiro",0,0,2]},{"code":401,"indent":0,"parameters":["\\n<汐 Shio>"]},{"code":401,"indent":0,"parameters":["\\}Great\\{<br>"]},{"code":401,"indent":0,"parameters":["好了"]},{"code":101,"indent":0,"parameters":["Hiiro",0,0,2]},{"code":401,"indent":0,"parameters":["\\n<汐 Shio>"]},{"code":401,"indent":0,"parameters":["\\}Hmm?\\{<br>"]},{"code":401,"indent":0,"parameters":["嗯？"]},{"code":101,"indent":0,"parameters":["Hiiro",0,0,2]},{"code":401,"indent":0,"parameters":["\\n<汐 Shio>"]},{"code":401,"indent":0,"parameters":["\\}Hmmmmm??\\{<br>"]},{"code":401,"indent":0,"parameters":["嗯嗯？？"]},{"code":101,"indent":0,"parameters":["Hiiro",0,0,2]},{"code":401,"indent":0,"parameters":["\\n<汐 Shio>"]},{"code":401,"indent":0,"parameters":["\\}Hmmmmmmm??\\{<br>"]},{"code":401,"indent":0,"parameters":["嗯嗯嗯？？？"]},{"code":101,"indent":0,"parameters":["Hiiro",0,0,2]},{"code":401,"indent":0,"parameters":["\\n<汐 Shio>"]},{"code":401,"indent":0,"parameters":["我有种不祥的预感"]},{"code":101,"indent":0,"parameters":["Hiiro",0,0,2]},{"code":401,"indent":0,"parameters":["\\n<汐 Shio>"]},{"code":401,"indent":0,"parameters":["……"]},{"code":225,"indent":0,"parameters":[9,9,45,true]},{"code":101,"indent":0,"parameters":["Hiiro",0,0,2]},{"code":401,"indent":0,"parameters":["\\n<汐 Shio>"]},{"code":401,"indent":0,"parameters":["\\}NO!!!!!!!!!!!!!!!!!!!!!!!!!!! WAY!!!!!!!!!!!!!!!!!!!!!!!!!\\{<br>"]},{"code":401,"indent":0,"parameters":["不！！！！！会！！！！！！！吧！！！！！！！！"]},{"code":101,"indent":0,"parameters":["Hiiro",0,0,2]},{"code":401,"indent":0,"parameters":["\\n<汐 Shio>"]},{"code":401,"indent":0,"parameters":["(\\}There’s no water inside??\\{<br>"]},{"code":401,"indent":0,"parameters":["没水了？？)"]},{"code":101,"indent":0,"parameters":["Hiiro",0,0,2]},{"code":401,"indent":0,"parameters":["\\n<汐 Shio>"]},{"code":401,"indent":0,"parameters":["(\\}There is no water inside!!!!!!!!\\{<br>"]},{"code":401,"indent":0,"parameters":["好像是真的没水了！！！！！)"]},{"code":101,"indent":0,"parameters":["Hiiro",0,0,2]},{"code":401,"indent":0,"parameters":["\\n<汐 Shio>"]},{"code":401,"indent":0,"parameters":["(\\}Well...\\{<br>"]},{"code":401,"indent":0,"parameters":["可能……)"]},{"code":101,"indent":0,"parameters":["Hiiro",0,0,2]},{"code":401,"indent":0,"parameters":["\\n<汐 Shio>"]},{"code":401,"indent":0,"parameters":["(\\}This is the end of the world, isn’t it?\\{<br>"]},{"code":401,"indent":0,"parameters":["这就是世界末日吧？)"]},{"code":101,"indent":0,"parameters":["Hiiro",0,0,2]},{"code":401,"indent":0,"parameters":["\\n<汐 Shio>"]},{"code":401,"indent":0,"parameters":["……"]},{"code":101,"indent":0,"parameters":["Hiiro",0,0,2]},{"code":401,"indent":0,"parameters":["\\n<汐 Shio>"]},{"code":401,"indent":0,"parameters":["先把马桶盖盖上吧"]},{"code":101,"indent":0,"parameters":["Hiiro",0,0,2]},{"code":401,"indent":0,"parameters":["\\n<汐 Shio>"]},{"code":401,"indent":0,"parameters":["(\\}Under such an emergency, I suddenly remember that I kind of want to be an engineer when I was little\\{<br>"]},{"code":401,"indent":0,"parameters":["在这种紧急的时刻，突然想到自己小时候曾经也理想着成为一名工程师)"]},{"code":101,"indent":0,"parameters":["Hiiro",0,0,2]},{"code":401,"indent":0,"parameters":["\\n<汐 Shio>"]},{"code":401,"indent":0,"parameters":["(\\}Wait? Did I have this kind of dream?\\{<br>"]},{"code":401,"indent":0,"parameters":["等等？真有这样的理想嘛？)"]},{"code":101,"indent":0,"parameters":["Hiiro",0,0,2]},{"code":401,"indent":0,"parameters":["\\n<汐 Shio>"]},{"code":401,"indent":0,"parameters":["(\\}Maybe not...\\{<br>"]},{"code":401,"indent":0,"parameters":["也许没有……)"]},{"code":101,"indent":0,"parameters":["Hiiro",0,0,2]},{"code":401,"indent":0,"parameters":["\\n<汐 Shio>"]},{"code":401,"indent":0,"parameters":["(\\}Maybe I’m just trying to make something up, as to rationalize the thing that I’m going to do next\\{<br>"]},{"code":401,"indent":0,"parameters":["可能只是为了合理化我现在正准备在做的这件事情而捏造的理由而已)"]},{"code":101,"indent":0,"parameters":["Hiiro",0,0,2]},{"code":401,"indent":0,"parameters":["\\n<汐 Shio>"]},{"code":401,"indent":0,"parameters":["(\\}Everything in this world should follow the rule of causality, this is my OCD\\{<br>"]},{"code":401,"indent":0,"parameters":["万事万物，都要有因有果，这是我的强迫症)"]},{"code":101,"indent":0,"parameters":["Hiiro",0,0,2]},{"code":401,"indent":0,"parameters":["\\n<汐 Shio>"]},{"code":401,"indent":0,"parameters":["(\\}All fates have their causes\\{<br>"]},{"code":401,"indent":0,"parameters":["即使是命中注定，也一定必有其因)"]},{"code":101,"indent":0,"parameters":["Hiiro",0,0,2]},{"code":401,"indent":0,"parameters":["\\n<汐 Shio>"]},{"code":401,"indent":0,"parameters":["\\}Ok...\\{<br>"]},{"code":401,"indent":0,"parameters":["好吧……"]},{"code":101,"indent":0,"parameters":["Hiiro",0,0,2]},{"code":401,"indent":0,"parameters":["\\n<汐 Shio>"]},{"code":401,"indent":0,"parameters":["(先打开水箱看看吧)"]},{"code":101,"indent":0,"parameters":["Hiiro",0,0,2]},{"code":401,"indent":0,"parameters":["\\n<汐 Shio>"]},{"code":401,"indent":0,"parameters":["(\\}This toilet... How long has it been used?\\{<br>"]},{"code":401,"indent":0,"parameters":["这马桶……用了多久来着？)"]},{"code":101,"indent":0,"parameters":["Hiiro",0,0,2]},{"code":401,"indent":0,"parameters":["\\n<汐 Shio>"]},{"code":401,"indent":0,"parameters":["(\\}Five years? Ten years?\\{<br>"]},{"code":401,"indent":0,"parameters":["五年？十年？)"]},{"code":101,"indent":0,"parameters":["Hiiro",0,0,2]},{"code":401,"indent":0,"parameters":["\\n<汐 Shio>"]},{"code":401,"indent":0,"parameters":["(\\}To be frank, which year did Yume Sakura Highschool was built?\\{<br>"]},{"code":401,"indent":0,"parameters":["说到底梦樱高校到底是哪年开始建立的？)"]},{"code":101,"indent":0,"parameters":["Hiiro",0,0,2]},{"code":401,"indent":0,"parameters":["\\n<汐 Shio>"]},{"code":401,"indent":0,"parameters":["(\\}Our school badge only has number of the current year\\{<br>"]},{"code":401,"indent":0,"parameters":["我们每个人的校徽都只有今年的年份)"]},{"code":101,"indent":0,"parameters":["Hiiro",0,0,2]},{"code":401,"indent":0,"parameters":["\\n<汐 Shio>"]},{"code":401,"indent":0,"parameters":["(\\}For example, the one on my shirt has 2021\\{<br>"]},{"code":401,"indent":0,"parameters":["比如我的，上面只写着2021)"]},{"code":101,"indent":0,"parameters":["Hiiro",0,0,2]},{"code":401,"indent":0,"parameters":["\\n<汐 Shio>"]},{"code":401,"indent":0,"parameters":["(\\}But our school can’t be built in 2021 right?\\{<br>"]},{"code":401,"indent":0,"parameters":["总不能是今年才建的吧？)"]},{"code":101,"indent":0,"parameters":["Hiiro",0,0,2]},{"code":401,"indent":0,"parameters":["\\n<汐 Shio>"]},{"code":401,"indent":0,"parameters":["(\\}Hahaha...\\{<br>"]},{"code":401,"indent":0,"parameters":["哈哈哈……)"]},{"code":101,"indent":0,"parameters":["Hiiro",0,0,2]},{"code":401,"indent":0,"parameters":["\\n<汐 Shio>"]},{"code":401,"indent":0,"parameters":["(\\}I really wish it was built this year, especially under my current circumstance...\\{<br>"]},{"code":401,"indent":0,"parameters":["这种时候倒是有点希望是今年才建的……)"]},{"code":101,"indent":0,"parameters":["Hiiro",0,0,2]},{"code":401,"indent":0,"parameters":["\\n<汐 Shio>"]},{"code":401,"indent":0,"parameters":["\\}Yeeeeee--------------\\{<br>"]},{"code":401,"indent":0,"parameters":["咿--------------------"]},{"code":101,"indent":0,"parameters":["Hiiro",0,0,2]},{"code":401,"indent":0,"parameters":["\\n<汐 Shio>"]},{"code":401,"indent":0,"parameters":["(\\}It’s a bit heavy\\{<br>"]},{"code":401,"indent":0,"parameters":["有点重)"]},{"code":101,"indent":0,"parameters":["Hiiro",0,0,2]},{"code":401,"indent":0,"parameters":["\\n<汐 Shio>"]},{"code":401,"indent":0,"parameters":["(\\}But now the lip of water tank is opened\\{<br>"]},{"code":401,"indent":0,"parameters":["终于把水箱盖掀开了)"]},{"code":101,"indent":0,"parameters":["Hiiro",0,0,2]},{"code":401,"indent":0,"parameters":["\\n<汐 Shio>"]},{"code":401,"indent":0,"parameters":["(\\}And...\\{<br>"]},{"code":401,"indent":0,"parameters":["里面……)"]},{"code":101,"indent":0,"parameters":["Hiiro",0,0,2]},{"code":401,"indent":0,"parameters":["\\n<汐 Shio>"]},{"code":401,"indent":0,"parameters":["(\\}There’s no water inside\\{<br>"]},{"code":401,"indent":0,"parameters":["不仅一滴水都不剩下)"]},{"code":101,"indent":0,"parameters":["Hiiro",0,0,2]},{"code":401,"indent":0,"parameters":["\\n<汐 Shio>"]},{"code":401,"indent":0,"parameters":["(\\}But there’s a green book...\\{<br>"]},{"code":401,"indent":0,"parameters":["而且还放了一本绿色外皮的东西)"]},{"code":101,"indent":0,"parameters":["Hiiro",0,0,2]},{"code":401,"indent":0,"parameters":["\\n<汐 Shio>"]},{"code":401,"indent":0,"parameters":["……"]},{"code":101,"indent":0,"parameters":["Hiiro",0,0,2]},{"code":401,"indent":0,"parameters":["\\n<汐 Shio>"]},{"code":401,"indent":0,"parameters":["(\\}Seems like a note book\\{<br>"]},{"code":401,"indent":0,"parameters":["好像是一本笔记本)"]},{"code":101,"indent":0,"parameters":["Hiiro",0,0,2]},{"code":401,"indent":0,"parameters":["\\n<汐 Shio>"]},{"code":401,"indent":0,"parameters":["(先拿出来看看下面还有没有堵住吧……)"]},{"code":101,"indent":0,"parameters":["Hiiro",0,0,2]},{"code":401,"indent":0,"parameters":["\\n<汐 Shio>"]},{"code":401,"indent":0,"parameters":["\\}Well... There’s no strange smell inside...\\{<br>"]},{"code":401,"indent":0,"parameters":["嗯……倒是没有什么味道……"]},{"code":101,"indent":0,"parameters":["Hiiro",0,0,2]},{"code":401,"indent":0,"parameters":["\\n<汐 Shio>"]},{"code":401,"indent":0,"parameters":["(\\}The truth is, this tank is even a bit new...\\{<br>"]},{"code":401,"indent":0,"parameters":["说实在的，这马桶水箱，看上去比较新……)"]},{"code":101,"indent":0,"parameters":["Hiiro",0,0,2]},{"code":401,"indent":0,"parameters":["\\n<汐 Shio>"]},{"code":401,"indent":0,"parameters":["(\\}Although it is a water tank...\\{<br>"]},{"code":401,"indent":0,"parameters":["虽然说是水箱……)"]},{"code":101,"indent":0,"parameters":["Hiiro",0,0,2]},{"code":401,"indent":0,"parameters":["\\n<汐 Shio>"]},{"code":401,"indent":0,"parameters":["(\\}But if you look closely, you can’t find any water stain\\{<br>"]},{"code":401,"indent":0,"parameters":["但仔细看，似乎根本看不出有什么水渍)"]},{"code":101,"indent":0,"parameters":["Hiiro",0,0,2]},{"code":401,"indent":0,"parameters":["\\n<汐 Shio>"]},{"code":401,"indent":0,"parameters":["(\\}It looks like...\\{<br>"]},{"code":401,"indent":0,"parameters":["就像是……)"]},{"code":101,"indent":0,"parameters":["Hiiro",0,0,2]},{"code":401,"indent":0,"parameters":["\\n<汐 Shio>"]},{"code":401,"indent":0,"parameters":["(\\}It looks like there has never been water in there\\{<br>"]},{"code":401,"indent":0,"parameters":["根本没有装过水)"]},{"code":101,"indent":0,"parameters":["Hiiro",0,0,2]},{"code":401,"indent":0,"parameters":["\\n<汐 Shio>"]},{"code":401,"indent":0,"parameters":["(应该是没修好的可能了)"]},{"code":101,"indent":0,"parameters":["Hiiro",0,0,2]},{"code":401,"indent":0,"parameters":["\\n<汐 Shio>"]},{"code":401,"indent":0,"parameters":["(\\}Hmm...\\{<br>"]},{"code":401,"indent":0,"parameters":["嗯……)"]},{"code":101,"indent":0,"parameters":["Hiiro",0,0,2]},{"code":401,"indent":0,"parameters":["\\n<汐 Shio>"]},{"code":401,"indent":0,"parameters":["(先看看那本笔记本吧)"]},{"code":101,"indent":0,"parameters":["",0,0,2]},{"code":401,"indent":0,"parameters":["<br>"]},{"code":401,"indent":0,"parameters":["\\}\\#“The Diary of God”\\{<br>"]},{"code":401,"indent":0,"parameters":["\\#“神之日记”"]},{"code":101,"indent":0,"parameters":["Hiiro",0,0,2]},{"code":401,"indent":0,"parameters":["\\n<汐 Shio>"]},{"code":401,"indent":0,"parameters":["\\}A Zhe...\\{<br>"]},{"code":401,"indent":0,"parameters":["啊这……"]},{"code":101,"indent":0,"parameters":["Hiiro",0,0,2]},{"code":401,"indent":0,"parameters":["\\n<汐 Shio>"]},{"code":401,"indent":0,"parameters":["(\\}But well, Highschool kids, they are now in the most Chuunibyou age you know\\{<br>"]},{"code":401,"indent":0,"parameters":["说来也是，高中生，正值最中二的年纪)"]},{"code":101,"indent":0,"parameters":["Hiiro",0,0,2]},{"code":401,"indent":0,"parameters":["\\n<汐 Shio>"]},{"code":401,"indent":0,"parameters":["(\\}It is not strange for them to do these kind of things\\{<br>"]},{"code":401,"indent":0,"parameters":["干出点这种事情也不奇怪)"]},{"code":101,"indent":0,"parameters":["Hiiro",0,0,2]},{"code":401,"indent":0,"parameters":["\\n<汐 Shio>"]},{"code":401,"indent":0,"parameters":["(\\}For example\\{<br>"]},{"code":401,"indent":0,"parameters":["比如说什么)"]},{"code":101,"indent":0,"parameters":["Hiiro",0,0,2]},{"code":401,"indent":0,"parameters":["\\n<汐 Shio>"]},{"code":401,"indent":0,"parameters":["(\\}Spend 10 RMB to buy a notebook on the street\\{<br>"]},{"code":401,"indent":0,"parameters":["故意在这里藏一本在路边10块钱就能买到的笔记本)"]},{"code":101,"indent":0,"parameters":["Hiiro",0,0,2]},{"code":401,"indent":0,"parameters":["\\n<汐 Shio>"]},{"code":401,"indent":0,"parameters":["(\\}Giving it a Chuunibyou title, and then hide it in here\\{<br>"]},{"code":401,"indent":0,"parameters":["写个中二的标题，藏在这里)"]},{"code":101,"indent":0,"parameters":["Hiiro",0,0,2]},{"code":401,"indent":0,"parameters":["\\n<汐 Shio>"]},{"code":401,"indent":0,"parameters":["(\\}And then go back to his class and says\\{<br>"]},{"code":401,"indent":0,"parameters":["然后在班里说)"]},{"code":101,"indent":0,"parameters":["Hiiro",0,0,2]},{"code":401,"indent":0,"parameters":["\\n<汐 Shio>"]},{"code":401,"indent":0,"parameters":["(\\}“Oh Hey, you know what, I heard that there’s a secret notebook in the boy’s restroom~”\\{<br>"]},{"code":401,"indent":0,"parameters":["“哦，哦，你们知不知道男厕所最里面马桶水箱里有一本神秘的笔记本~”)"]},{"code":101,"indent":0,"parameters":["Hiiro",0,0,2]},{"code":401,"indent":0,"parameters":["\\n<汐 Shio>"]},{"code":401,"indent":0,"parameters":["(\\}“Those who have seen it will die tonight~”\\{<br>"]},{"code":401,"indent":0,"parameters":["“只要看过的人都会在今晚死掉~‘)"]},{"code":101,"indent":0,"parameters":["Hiiro",0,0,2]},{"code":401,"indent":0,"parameters":["\\n<汐 Shio>"]},{"code":401,"indent":0,"parameters":["(\\}Things like that...\\{<br>"]},{"code":401,"indent":0,"parameters":["诸如此类……)"]},{"code":101,"indent":0,"parameters":["Hiiro",0,0,2]},{"code":401,"indent":0,"parameters":["\\n<汐 Shio>"]},{"code":401,"indent":0,"parameters":["(可是我还是很好奇里面写了什么)"]},{"code":101,"indent":0,"parameters":["Hiiro",0,0,2]},{"code":401,"indent":0,"parameters":["\\n<汐 Shio>"]},{"code":401,"indent":0,"parameters":["(\\}Well, just to take a look. It won’t bite me\\{<br>"]},{"code":401,"indent":0,"parameters":["嘛，就看一眼，看一眼又不会怎样)"]},{"code":101,"indent":0,"parameters":["Hiiro",0,0,2]},{"code":401,"indent":0,"parameters":["\\n<汐 Shio>"]},{"code":401,"indent":0,"parameters":["(\\}My IQ is at a different level with them anyway\\{<br>"]},{"code":401,"indent":0,"parameters":["反正我和他们的智商是不一样的)"]},{"code":101,"indent":0,"parameters":["Hiiro",0,0,2]},{"code":401,"indent":0,"parameters":["\\n<汐 Shio>"]},{"code":401,"indent":0,"parameters":["(\\Yes, this is called getting to know the thoughts of Chuunibyou high school student\\{<br>"]},{"code":401,"indent":0,"parameters":["嗯嗯，我这叫了解中二高中生的想法)"]},{"code":101,"indent":0,"parameters":["Hiiro",0,0,2]},{"code":401,"indent":0,"parameters":["\\n<汐 Shio>"]},{"code":401,"indent":0,"parameters":["(\\}Wait, I’m also a high school student\\{<br>"]},{"code":401,"indent":0,"parameters":["等等，我不就是高中生嘛)"]},{"code":101,"indent":0,"parameters":["",0,1,1]},{"code":401,"indent":0,"parameters":["<br>"]},{"code":401,"indent":0,"parameters":["\\#······"]},{"code":101,"indent":0,"parameters":["Hiiro",0,0,2]},{"code":401,"indent":0,"parameters":["\\n<汐 Shio>"]},{"code":401,"indent":0,"parameters":["\\}Iet me see...\\{<br>"]},{"code":401,"indent":0,"parameters":["看看..."]},{"code":101,"indent":0,"parameters":["",0,0,2]},{"code":401,"indent":0,"parameters":["\\}Page 1\\{<br>"]},{"code":401,"indent":0,"parameters":["第一页"]},{"code":101,"indent":0,"parameters":["",0,0,2]},{"code":401,"indent":0,"parameters":["\\}Empty...\\{<br>"]},{"code":401,"indent":0,"parameters":["空白……"]},{"code":101,"indent":0,"parameters":["",0,0,2]},{"code":401,"indent":0,"parameters":["\\}Page 2\\{<br>"]},{"code":401,"indent":0,"parameters":["第二页"]},{"code":101,"indent":0,"parameters":["",0,0,2]},{"code":401,"indent":0,"parameters":["\\}Empty...\\{<br>"]},{"code":401,"indent":0,"parameters":["空白……"]},{"code":101,"indent":0,"parameters":["",0,0,2]},{"code":401,"indent":0,"parameters":["\\}Page 3\\{<br>"]},{"code":401,"indent":0,"parameters":["第三页"]},{"code":101,"indent":0,"parameters":["",0,0,2]},{"code":401,"indent":0,"parameters":["\\}Empty...\\{<br>"]},{"code":401,"indent":0,"parameters":["空白……"]},{"code":101,"indent":0,"parameters":["",0,1,1]},{"code":401,"indent":0,"parameters":["<br>"]},{"code":401,"indent":0,"parameters":["\\#······"]},{"code":101,"indent":0,"parameters":["Hiiro",0,0,2]},{"code":401,"indent":0,"parameters":["\\n<汐 Shio>"]},{"code":401,"indent":0,"parameters":["\\}Nothing there\\{<br>"]},{"code":401,"indent":0,"parameters":["什么都没有嘛"]},{"code":101,"indent":0,"parameters":["Hiiro",0,0,2]},{"code":401,"indent":0,"parameters":["\\n<汐 Shio>"]},{"code":401,"indent":0,"parameters":["\\}Such a poorly made prank\\{<br>"]},{"code":401,"indent":0,"parameters":["恶作剧也太没有诚意了"]},{"code":101,"indent":0,"parameters":["",0,0,2]},{"code":401,"indent":0,"parameters":["\\}Page 4\\{<br>"]},{"code":401,"indent":0,"parameters":["第四页"]},{"code":101,"indent":0,"parameters":["",0,0,2]},{"code":401,"indent":0,"parameters":["\\}“March 15th “\\{<br>"]},{"code":401,"indent":0,"parameters":["“3月15日“"]},{"code":101,"indent":0,"parameters":["",0,0,2]},{"code":401,"indent":0,"parameters":["\\}“Rain”\\{<br>"]},{"code":401,"indent":0,"parameters":["“下雨”"]},{"code":101,"indent":0,"parameters":["Hiiro",0,0,2]},{"code":401,"indent":0,"parameters":["\\n<汐 Shio>"]},{"code":401,"indent":0,"parameters":["(\\}Uhhh...\\{<br>"]},{"code":401,"indent":0,"parameters":["额……)"]},{"code":101,"indent":0,"parameters":["Hiiro",0,0,2]},{"code":401,"indent":0,"parameters":["\\n<汐 Shio>"]},{"code":401,"indent":0,"parameters":["(\\}I don’t know where I should start from...\\{<br>"]},{"code":401,"indent":0,"parameters":["不知道该从哪里开始吐槽……)"]},{"code":101,"indent":0,"parameters":["Hiiro",0,0,2]},{"code":401,"indent":0,"parameters":["\\n<汐 Shio>"]},{"code":401,"indent":0,"parameters":["(\\}Disappointing, I have to say\\{<br>"]},{"code":401,"indent":0,"parameters":["也有可能是因为失望)"]},{"code":101,"indent":0,"parameters":["Hiiro",0,0,2]},{"code":401,"indent":0,"parameters":["\\n<汐 Shio>"]},{"code":401,"indent":0,"parameters":["(\\}I thought I have found a treasure \\{<br>"]},{"code":401,"indent":0,"parameters":["明明是找到了宝藏的心情)"]},{"code":101,"indent":0,"parameters":["Hiiro",0,0,2]},{"code":401,"indent":0,"parameters":["\\n<汐 Shio>"]},{"code":401,"indent":0,"parameters":["(\\}But it turns out to be a trash\\{<br>"]},{"code":401,"indent":0,"parameters":["结果打开你却给我看这个)"]},{"code":101,"indent":0,"parameters":["Hiiro",0,0,2]},{"code":401,"indent":0,"parameters":["\\n<汐 Shio>"]},{"code":401,"indent":0,"parameters":["(\\}What an awful day...\\{<br>"]},{"code":401,"indent":0,"parameters":["真是糟糕的一天……)"]},{"code":101,"indent":0,"parameters":["Hiiro",0,0,2]},{"code":401,"indent":0,"parameters":["\\n<汐 Shio>"]},{"code":401,"indent":0,"parameters":["(\\}But... how should I even flush this toilet...\\{<br>"]},{"code":401,"indent":0,"parameters":["可是……冲水怎么办……)"]},{"code":101,"indent":0,"parameters":["Hiiro",0,0,2]},{"code":401,"indent":0,"parameters":["\\n<汐 Shio>"]},{"code":401,"indent":0,"parameters":["……"]},{"code":101,"indent":0,"parameters":["Hiiro",0,0,2]},{"code":401,"indent":0,"parameters":["\\n<汐 Shio>"]},{"code":401,"indent":0,"parameters":["……"]},{"code":101,"indent":0,"parameters":["Hiiro",0,0,2]},{"code":401,"indent":0,"parameters":["\\n<汐 Shio>"]},{"code":401,"indent":0,"parameters":["……"]},{"code":101,"indent":0,"parameters":["Hiiro",0,0,2]},{"code":401,"indent":0,"parameters":["\\n<汐 Shio>"]},{"code":401,"indent":0,"parameters":["(\\}How\\{<br>"]},{"code":401,"indent":0,"parameters":["能怎么办)"]},{"code":101,"indent":0,"parameters":["Hiiro",0,0,2]},{"code":401,"indent":0,"parameters":["\\n<汐 Shio>"]},{"code":401,"indent":0,"parameters":["……"]},{"code":101,"indent":0,"parameters":["Hiiro",0,0,2]},{"code":401,"indent":0,"parameters":["\\n<汐 Shio>"]},{"code":401,"indent":0,"parameters":["……"]},{"code":101,"indent":0,"parameters":["Hiiro",0,0,2]},{"code":401,"indent":0,"parameters":["\\n<汐 Shio>"]},{"code":401,"indent":0,"parameters":["……"]},{"code":101,"indent":0,"parameters":["Hiiro",0,0,2]},{"code":401,"indent":0,"parameters":["\\n<汐 Shio>"]},{"code":401,"indent":0,"parameters":["(\\}I really want to kill myself at this moment\\{<br>"]},{"code":401,"indent":0,"parameters":["这一刻，我想把我自己一刀捅死)"]},{"code":101,"indent":0,"parameters":["Hiiro",0,0,2]},{"code":401,"indent":0,"parameters":["\\n<汐 Shio>"]},{"code":401,"indent":0,"parameters":["(\\}This feeling is like...\\{<br>"]},{"code":401,"indent":0,"parameters":["大概就是那种……)"]},{"code":101,"indent":0,"parameters":["Hiiro",0,0,2]},{"code":401,"indent":0,"parameters":["\\n<汐 Shio>"]},{"code":401,"indent":0,"parameters":["(\\}If now there’s a groundhog\\{<br>"]},{"code":401,"indent":0,"parameters":["如果现在有一只土拨鼠)"]},{"code":101,"indent":0,"parameters":["Hiiro",0,0,2]},{"code":401,"indent":0,"parameters":["\\n<汐 Shio>"]},{"code":401,"indent":0,"parameters":["(\\}which can dig a hole from the Eastern Hemisphere to the Western Hemisphere\\{<br>"]},{"code":401,"indent":0,"parameters":["能从东半球直线挖到西半球)"]},{"code":101,"indent":0,"parameters":["Hiiro",0,0,2]},{"code":401,"indent":0,"parameters":["\\n<汐 Shio>"]},{"code":401,"indent":0,"parameters":["(\\}I will definitely go with him\\{<br>"]},{"code":401,"indent":0,"parameters":["我想和它一起去的那种)"]},{"code":101,"indent":0,"parameters":["Hiiro",0,0,2]},{"code":401,"indent":0,"parameters":["\\n<汐 Shio>"]},{"code":401,"indent":0,"parameters":["\\}Groundhog San... Please help me...\\{<br>"]},{"code":401,"indent":0,"parameters":["土拨鼠先生……救救我……"]},{"code":101,"indent":0,"parameters":["Hiiro",0,0,2]},{"code":401,"indent":0,"parameters":["\\n<汐 Shio>"]},{"code":401,"indent":0,"parameters":["……"]},{"code":101,"indent":0,"parameters":["Hiiro",0,0,2]},{"code":401,"indent":0,"parameters":["\\n<汐 Shio>"]},{"code":401,"indent":0,"parameters":["(\\}Is there someone else in the toliet\\{<br>"]},{"code":401,"indent":0,"parameters":["有人在厕所外面吗？)"]},{"code":101,"indent":0,"parameters":["Hiiro",0,0,2]},{"code":401,"indent":0,"parameters":["\\n<汐 Shio>"]},{"code":401,"indent":0,"parameters":["(\\}I should check from beneath the door...\\{<br>"]},{"code":401,"indent":0,"parameters":["我得从底下门缝看看……)"]},{"code":101,"indent":0,"parameters":["Hiiro",0,0,2]},{"code":401,"indent":0,"parameters":["\\n<汐 Shio>"]},{"code":401,"indent":0,"parameters":["(\\}Seems like no one is here..\\{<br>"]},{"code":401,"indent":0,"parameters":["好像没有人……)"]},{"code":101,"indent":0,"parameters":["Hiiro",0,0,2]},{"code":401,"indent":0,"parameters":["\\n<汐 Shio>"]},{"code":401,"indent":0,"parameters":["……"]},{"code":101,"indent":0,"parameters":["Hiiro",0,0,2]},{"code":401,"indent":0,"parameters":["\\n<汐 Shio>"]},{"code":401,"indent":0,"parameters":["(\\}I gotta move fast!\\{<br>"]},{"code":401,"indent":0,"parameters":["此时不干，更待何时！"]},{"code":101,"indent":0,"parameters":["Hiiro",0,0,2]},{"code":401,"indent":0,"parameters":["\\n<汐 Shio>"]},{"code":401,"indent":0,"parameters":["(\\}Why am I doing this?\\{<br>"]},{"code":401,"indent":0,"parameters":["为什么要这么鬼鬼祟祟呢？)"]},{"code":101,"indent":0,"parameters":["Hiiro",0,0,2]},{"code":401,"indent":0,"parameters":["\\n<汐 Shio>"]},{"code":401,"indent":0,"parameters":["(\\}Because I’m smart enough to come up with a brilliant idea\\{<br>"]},{"code":401,"indent":0,"parameters":["因为机智的我突然想到)"]},{"code":101,"indent":0,"parameters":["Hiiro",0,0,2]},{"code":401,"indent":0,"parameters":["\\n<汐 Shio>"]},{"code":401,"indent":0,"parameters":["(\\}There is a water bucket with a bailer inside right next to a sink in all restrooms\\{<br>"]},{"code":401,"indent":0,"parameters":["所有厕所的洗手池的旁边都有一个水瓢和水桶)"]},{"code":101,"indent":0,"parameters":["Hiiro",0,0,2]},{"code":401,"indent":0,"parameters":["\\n<汐 Shio>"]},{"code":401,"indent":0,"parameters":["(\\}Well, at least for all girl’s restroom\\{<br>"]},{"code":401,"indent":0,"parameters":["嘛，至少女生厕所是这样的)"]},{"code":101,"indent":0,"parameters":["Hiiro",0,0,2]},{"code":401,"indent":0,"parameters":["\\n<汐 Shio>"]},{"code":401,"indent":0,"parameters":["(\\}Well, at least for all girl’s restroom\\{<br>"]},{"code":401,"indent":0,"parameters":["嘛，至少女生厕所是这样的)"]},{"code":201,"indent":0,"parameters":[0,41,4,10,2,0]},{"code":222,"indent":0,"parameters":[]},{"code":101,"indent":0,"parameters":["Hiiro",0,0,2]},{"code":401,"indent":0,"parameters":["\\n<汐 Shio>"]},{"code":401,"indent":0,"parameters":["(\\}I need to run before being spotted by anyone!\\{<br>"]},{"code":401,"indent":0,"parameters":["在还没有被发现之前，赶紧溜了吧！"]},{"code":121,"indent":0,"parameters":[13,13,1]},{"code":121,"indent":0,"parameters":[14,14,0]},{"code":123,"indent":0,"parameters":["A",0]},{"code":0,"indent":0,"parameters":[]}],"moveFrequency":3,"moveRoute":{"list":[{"code":0,"parameters":[]}],"repeat":true,"skippable":false,"wait":false},"moveSpeed":3,"moveType":0,"priorityType":1,"stepAnime":false,"through":false,"trigger":0,"walkAnime":true},{"conditions":{"actorId":1,"actorValid":false,"itemId":1,"itemValid":false,"selfSwitchCh":"A","selfSwitchValid":true,"switch1Id":1,"switch1Valid":false,"switch2Id":1,"switch2Valid":false,"variableId":1,"variableValid":false,"variableValue":0},"directionFix":false,"image":{"characterIndex":0,"characterName":"","direction":2,"pattern":0,"tileId":0},"list":[{"code":0,"indent":0,"parameters":[]}],"moveFrequency":3,"moveRoute":{"list":[{"code":0,"parameters":[]}],"repeat":true,"skippable":false,"wait":false},"moveSpeed":3,"moveType":0,"priorityType":0,"stepAnime":false,"through":false,"trigger":0,"walkAnime":true}],"x":7,"y":3}
]
}